routerscraper/__init__.py
routerscraper/basescraper.py
routerscraper/dataTypes.py
routerscraper/fastgate_dn8245f2.py
routerscraper/requestscraper.py
routerscraper/seleniumscraper.py
routerscraper/technicolor_tg789vacv2.py
routerscraper/tplink_m7000.py
routerscraper-0.3.1.dist-info/METADATA
routerscraper-0.3.1.dist-info/WHEEL
routerscraper-0.3.1.dist-info/top_level.txt
routerscraper-0.3.1.dist-info/RECORD
