Metadata-Version: 2.1
Name: routerscraper
Version: 0.3.1
Summary: A python package to interact with different routers
Author: fra87
License: MIT License
Project-URL: Homepage, https://github.com/fra87/RouterScraper
Keywords: router,scraping,scrape,harvest
Classifier: Development Status :: 3 - Alpha
Classifier: License :: OSI Approved :: MIT License
Classifier: Operating System :: OS Independent
Classifier: Programming Language :: Python
Classifier: Programming Language :: Python :: 3
Classifier: Programming Language :: Python :: 3.7
Classifier: Programming Language :: Python :: 3.8
Classifier: Programming Language :: Python :: 3.9
Classifier: Programming Language :: Python :: 3.10
Classifier: Topic :: Software Development :: Libraries :: Python Modules
Classifier: Topic :: System :: Networking :: Monitoring
Requires-Python: >=3.7
Requires-Dist: srp
Requires-Dist: beautifulsoup4
Requires-Dist: requests
Requires-Dist: selenium
Provides-Extra: dev
Requires-Dist: flake8 ; extra == 'dev'
Requires-Dist: reuse ; extra == 'dev'
Requires-Dist: bumpver ; extra == 'dev'
Requires-Dist: build ; extra == 'dev'
Requires-Dist: twine ; extra == 'dev'
Requires-Dist: pip ; extra == 'dev'
Requires-Dist: setuptools ; extra == 'dev'
Requires-Dist: wheel ; extra == 'dev'
